deepfastvision/__init__.py
deepfastvision/core/DeepTransferClassification.py
deepfastvision/core/__init__.py
deepfastvision/data_management/__init__.py
deepfastvision/data_management/data_helpers.py
deepfastvision/model_components/__init__.py
deepfastvision/model_components/export_helpers.py
deepfastvision/model_components/model_creation.py
deepfastvision/model_components/prediction_helpers.py
deepfastvision/model_components/callbacks/__init__.py
deepfastvision/model_components/callbacks/custom_save_weights.py
deepfastvision/model_components/preprocessing/__init__.py
deepfastvision/model_components/preprocessing/preprocessing.py
deepfastvision/plotting/__init__.py
deepfastvision/plotting/plot_helpers.py
deepfastvision-1.0.2.3.dist-info/LICENSE
deepfastvision-1.0.2.3.dist-info/METADATA
deepfastvision-1.0.2.3.dist-info/WHEEL
deepfastvision-1.0.2.3.dist-info/top_level.txt
deepfastvision-1.0.2.3.dist-info/RECORD
